Material5/synth4B.v
`include "mycells.v"
/* Generated by Yosys 0.7 (git sha1 61f6811, gcc 4.8.4-2ubuntu1~14.04.3 -O2 -fstack-protector -fPIC -Os) */

(* top =  1  *)
(* src = "register.v:1" *)
module reg_desp(q, s_out, clk, enb, dir, s_in, mode, d);
  (* src = "register.v:7" *)
  wire [3:0] _000_;
  (* src = "register.v:7" *)
  wire _001_;
  wire _002_;
  wire _003_;
  wire _004_;
  wire _005_;
  wire _006_;
  wire _007_;
  wire _008_;
  wire _009_;
  wire _010_;
  wire _011_;
  wire _012_;
  wire _013_;
  wire _014_;
  wire _015_;
  wire _016_;
  wire _017_;
  wire _018_;
  wire _019_;
  wire _020_;
  wire _021_;
  wire _022_;
  wire _023_;
  wire _024_;
  wire _025_;
  wire _026_;
  wire _027_;
  wire _028_;
  wire _029_;
  wire _030_;
  wire _031_;
  wire _032_;
  wire _033_;
  wire _034_;
  wire _035_;
  wire _036_;
  wire _037_;
  wire _038_;
  wire _039_;
  wire _040_;
  wire _041_;
  wire _042_;
  wire _043_;
  wire _044_;
  wire _045_;
  wire _046_;
  wire _047_;
  wire _048_;
  wire _049_;
  wire _050_;
  wire _051_;
  wire _052_;
  wire _053_;
  wire _054_;
  wire _055_;
  wire _056_;
  wire _057_;
  wire _058_;
  wire _059_;
  wire _060_;
  wire _061_;
  wire _062_;
  wire _063_;
  wire _064_;
  wire _065_;
  wire _066_;
  (* src = "register.v:2" *)
  input clk;
  (* src = "register.v:4" *)
  input [3:0] d;
  (* src = "register.v:2" *)
  input dir;
  (* src = "register.v:2" *)
  input enb;
  (* src = "register.v:3" *)
  input [1:0] mode;
  (* src = "register.v:5" *)
  output [3:0] q;
  (* src = "register.v:2" *)
  input s_in;
  (* src = "register.v:6" *)
  output s_out;
  NOT _067_ (
    .A(enb),
    .Y(_002_)
  );
  NOT _068_ (
    .A(mode[0]),
    .Y(_003_)
  );
  NOT _069_ (
    .A(mode[1]),
    .Y(_004_)
  );
  NOR _070_ (
    .A(_004_),
    .B(_003_),
    .Y(_005_)
  );
  NOR _071_ (
    .A(_005_),
    .B(_002_),
    .Y(_006_)
  );
  NOT _072_ (
    .A(_006_),
    .Y(_007_)
  );
  NAND _073_ (
    .A(_007_),
    .B(s_out),
    .Y(_008_)
  );
  NOT _074_ (
    .A(dir),
    .Y(_009_)
  );
  NAND _075_ (
    .A(_009_),
    .B(q[3]),
    .Y(_010_)
  );
  NAND _076_ (
    .A(dir),
    .B(q[0]),
    .Y(_011_)
  );
  NAND _077_ (
    .A(_011_),
    .B(_010_),
    .Y(_012_)
  );
  NOR _078_ (
    .A(mode[1]),
    .B(mode[0]),
    .Y(_013_)
  );
  NOT _079_ (
    .A(_013_),
    .Y(_014_)
  );
  NOR _080_ (
    .A(_014_),
    .B(_002_),
    .Y(_015_)
  );
  NAND _081_ (
    .A(_015_),
    .B(_012_),
    .Y(_016_)
  );
  NAND _082_ (
    .A(_016_),
    .B(_008_),
    .Y(_001_)
  );
  NAND _083_ (
    .A(_002_),
    .B(q[0]),
    .Y(_017_)
  );
  NOR _084_ (
    .A(mode[1]),
    .B(_003_),
    .Y(_018_)
  );
  NAND _085_ (
    .A(q[1]),
    .B(dir),
    .Y(_019_)
  );
  NAND _086_ (
    .A(_019_),
    .B(_010_),
    .Y(_020_)
  );
  NAND _087_ (
    .A(_020_),
    .B(_018_),
    .Y(_021_)
  );
  NOT _088_ (
    .A(d[0]),
    .Y(_022_)
  );
  NOR _089_ (
    .A(_004_),
    .B(mode[0]),
    .Y(_023_)
  );
  NAND _090_ (
    .A(_023_),
    .B(_022_),
    .Y(_024_)
  );
  NAND _091_ (
    .A(q[0]),
    .B(mode[1]),
    .Y(_025_)
  );
  NAND _092_ (
    .A(_025_),
    .B(mode[0]),
    .Y(_026_)
  );
  NAND _093_ (
    .A(_026_),
    .B(_024_),
    .Y(_027_)
  );
  NAND _094_ (
    .A(_027_),
    .B(_021_),
    .Y(_028_)
  );
  NOT _095_ (
    .A(s_in),
    .Y(_029_)
  );
  NOR _096_ (
    .A(_029_),
    .B(dir),
    .Y(_030_)
  );
  NAND _097_ (
    .A(_019_),
    .B(_013_),
    .Y(_031_)
  );
  NOR _098_ (
    .A(_031_),
    .B(_030_),
    .Y(_032_)
  );
  NOR _099_ (
    .A(_032_),
    .B(_002_),
    .Y(_033_)
  );
  NAND _100_ (
    .A(_033_),
    .B(_028_),
    .Y(_034_)
  );
  NAND _101_ (
    .A(_034_),
    .B(_017_),
    .Y(_000_[0])
  );
  NOR _102_ (
    .A(_006_),
    .B(q[1]),
    .Y(_035_)
  );
  NAND _103_ (
    .A(mode[1]),
    .B(_003_),
    .Y(_036_)
  );
  NOR _104_ (
    .A(_036_),
    .B(d[1]),
    .Y(_037_)
  );
  NAND _105_ (
    .A(q[2]),
    .B(dir),
    .Y(_038_)
  );
  NAND _106_ (
    .A(_009_),
    .B(q[0]),
    .Y(_039_)
  );
  NAND _107_ (
    .A(_039_),
    .B(_038_),
    .Y(_040_)
  );
  NOR _108_ (
    .A(_040_),
    .B(mode[1]),
    .Y(_041_)
  );
  NOR _109_ (
    .A(_041_),
    .B(_037_),
    .Y(_042_)
  );
  NOR _110_ (
    .A(_042_),
    .B(_002_),
    .Y(_043_)
  );
  NOR _111_ (
    .A(_043_),
    .B(_035_),
    .Y(_000_[1])
  );
  NOR _112_ (
    .A(_006_),
    .B(q[2]),
    .Y(_044_)
  );
  NOR _113_ (
    .A(_036_),
    .B(d[2]),
    .Y(_045_)
  );
  NAND _114_ (
    .A(dir),
    .B(q[3]),
    .Y(_046_)
  );
  NAND _115_ (
    .A(q[1]),
    .B(_009_),
    .Y(_047_)
  );
  NAND _116_ (
    .A(_047_),
    .B(_046_),
    .Y(_048_)
  );
  NOR _117_ (
    .A(_048_),
    .B(mode[1]),
    .Y(_049_)
  );
  NOR _118_ (
    .A(_049_),
    .B(_045_),
    .Y(_050_)
  );
  NOR _119_ (
    .A(_050_),
    .B(_002_),
    .Y(_051_)
  );
  NOR _120_ (
    .A(_051_),
    .B(_044_),
    .Y(_000_[2])
  );
  NAND _121_ (
    .A(_002_),
    .B(q[3]),
    .Y(_052_)
  );
  NAND _122_ (
    .A(q[2]),
    .B(_009_),
    .Y(_053_)
  );
  NAND _123_ (
    .A(_053_),
    .B(_011_),
    .Y(_054_)
  );
  NAND _124_ (
    .A(_054_),
    .B(_018_),
    .Y(_055_)
  );
  NOT _125_ (
    .A(d[3]),
    .Y(_056_)
  );
  NAND _126_ (
    .A(_023_),
    .B(_056_),
    .Y(_057_)
  );
  NAND _127_ (
    .A(q[3]),
    .B(mode[1]),
    .Y(_058_)
  );
  NAND _128_ (
    .A(_058_),
    .B(mode[0]),
    .Y(_059_)
  );
  NAND _129_ (
    .A(_059_),
    .B(_057_),
    .Y(_060_)
  );
  NAND _130_ (
    .A(_060_),
    .B(_055_),
    .Y(_061_)
  );
  NOR _131_ (
    .A(_029_),
    .B(_009_),
    .Y(_062_)
  );
  NAND _132_ (
    .A(_053_),
    .B(_013_),
    .Y(_063_)
  );
  NOR _133_ (
    .A(_063_),
    .B(_062_),
    .Y(_064_)
  );
  NOR _134_ (
    .A(_064_),
    .B(_002_),
    .Y(_065_)
  );
  NAND _135_ (
    .A(_065_),
    .B(_061_),
    .Y(_066_)
  );
  NAND _136_ (
    .A(_066_),
    .B(_052_),
    .Y(_000_[3])
  );
  DFF _137_ (
    .C(clk),
    .D(_000_[0]),
    .Q(q[0])
  );
  DFF _138_ (
    .C(clk),
    .D(_000_[1]),
    .Q(q[1])
  );
  DFF _139_ (
    .C(clk),
    .D(_000_[2]),
    .Q(q[2])
  );
  DFF _140_ (
    .C(clk),
    .D(_000_[3]),
    .Q(q[3])
  );
  DFF _141_ (
    .C(clk),
    .D(_001_),
    .Q(s_out)
  );
endmodule

Material5/tester4B.v
module tester(clk,enb,dir,s_in,mode,d);
output reg clk,enb,dir,s_in;
output reg [1:0] mode;
output reg [3:0] d;


//Senal de reloj
always #5 clk = !clk;

//valores iniciales
initial begin
    clk<=0;
    enb <= 0;
    dir <= 0;
    s_in <= 1;
    mode <= 2'b00;

  $display("Inicia prueba #5, carga en paralelo");
  mode <= 2'b10;
  enb <= 1'b1;
  d<=4'b1010;
  #10 ;

  $display("Inicia prueba #1, rotacion a la izquierda");
  mode <= 2'b00;
  #40;

  $display("Inicia prueba #5, carga en paralelo");
  mode <= 2'b10;
  d<=4'b1010;
  #10;

  $display("Inicia prueba #2, rotacion a la derecha");
  mode <= 2'b00;
  dir    <= 1'b1;
  #40;

  $display("Inicia prueba #5, carga en paralelo");
  mode <= 2'b10;
  d <=4'b0001;
  #10;

  $display("Inicia prueba #3, rotacion circular a la izquierda");
  mode <= 2'b01;
  dir    <= 1'b0;
  #40;

  $display("Inicia prueba #4, rotacion circular a la derecha");
  mode <= 2'b01;
  dir    <= 1'b1;
  #40 $finish;
    end
endmodule

Material5/register4B_tb.v
module testbench();

wire [1:0] mode;
wire [3:0] d;
output wire [3:0] q;

tester tst1(clk,enb,dir,s_in,mode,d);
reg_desp reg1(q,s_out,clk,enb,dir,s_in,mode,d);


initial
  begin
    $dumpfile("register.vcd");
    $dumpvars;
    $display ("time\t clk enb dir mode d s_in q s_out");
    $monitor ("%g\t    %b  %b  %b  %b %b %b %b  %b",
    $time, clk, enb, dir, mode, d, s_in, q, s_out);

  end


endmodule

Material5/mycells.v
`timescale 1ns / 1ps
module BUF(A, Y);
input A;
output Y;
assign Y = A;
endmodule

module NOT(A, Y);
input A;
output Y;
assign #50 Y = ~A;
endmodule

module NAND(A, B, Y);
input A, B;
output Y;
assign #25 Y = ~(A & B);
endmodule

module NOR(A, B, Y);
input A, B;
output Y;
assign #60 Y = ~(A | B);
endmodule

module DFF(C, D, Q);
input C, D;
output reg Q;
always @(posedge C)
        Q <= D;
endmodule

module DFFSR(C, D, Q, S, R);
input C, D, S, R;
output reg Q;
always @(posedge C, posedge S, posedge R)
        if (S)
                Q <= 1'b1;
        else if (R)
                Q <= 1'b0;
        else
                Q <= D;
endmodule

Material5/register.vcd
$date
	Fri May 12 03:57:58 2017
$end
$version
	Icarus Verilog
$end
$timescale
	1s
$end
$scope module BUF $end
$var wire 1 ! A $end
$var wire 1 " Y $end
$upscope $end
$scope module DFFSR $end
$var wire 1 # C $end
$var wire 1 $ D $end
$var wire 1 % R $end
$var wire 1 & S $end
$var reg 1 ' Q $end
$upscope $end
$scope module testbench $end
$var wire 1 ( clk $end
$var wire 4 ) d [3:0] $end
$var wire 1 * dir $end
$var wire 1 + enb $end
$var wire 2 , mode [1:0] $end
$var wire 4 - q [3:0] $end
$var wire 1 . s_in $end
$var wire 1 / s_out $end
$scope module tst1 $end
$var reg 1 0 clk $end
$var reg 4 1 d [3:0] $end
$var reg 1 2 dir $end
$var reg 1 3 enb $end
$var reg 2 4 mode [1:0] $end
$var reg 1 5 s_in $end
$upscope $end
$scope module reg1 $end
$var wire 4 6 _000_ [3:0] $end
$var wire 1 7 _001_ $end
$var wire 1 8 _002_ $end
$var wire 1 9 _003_ $end
$var wire 1 : _004_ $end
$var wire 1 ; _005_ $end
$var wire 1 < _006_ $end
$var wire 1 = _007_ $end
$var wire 1 > _008_ $end
$var wire 1 ? _009_ $end
$var wire 1 @ _010_ $end
$var wire 1 A _011_ $end
$var wire 1 B _012_ $end
$var wire 1 C _013_ $end
$var wire 1 D _014_ $end
$var wire 1 E _015_ $end
$var wire 1 F _016_ $end
$var wire 1 G _017_ $end
$var wire 1 H _018_ $end
$var wire 1 I _019_ $end
$var wire 1 J _020_ $end
$var wire 1 K _021_ $end
$var wire 1 L _022_ $end
$var wire 1 M _023_ $end
$var wire 1 N _024_ $end
$var wire 1 O _025_ $end
$var wire 1 P _026_ $end
$var wire 1 Q _027_ $end
$var wire 1 R _028_ $end
$var wire 1 S _029_ $end
$var wire 1 T _030_ $end
$var wire 1 U _031_ $end
$var wire 1 V _032_ $end
$var wire 1 W _033_ $end
$var wire 1 X _034_ $end
$var wire 1 Y _035_ $end
$var wire 1 Z _036_ $end
$var wire 1 [ _037_ $end
$var wire 1 \ _038_ $end
$var wire 1 ] _039_ $end
$var wire 1 ^ _040_ $end
$var wire 1 _ _041_ $end
$var wire 1 ` _042_ $end
$var wire 1 a _043_ $end
$var wire 1 b _044_ $end
$var wire 1 c _045_ $end
$var wire 1 d _046_ $end
$var wire 1 e _047_ $end
$var wire 1 f _048_ $end
$var wire 1 g _049_ $end
$var wire 1 h _050_ $end
$var wire 1 i _051_ $end
$var wire 1 j _052_ $end
$var wire 1 k _053_ $end
$var wire 1 l _054_ $end
$var wire 1 m _055_ $end
$var wire 1 n _056_ $end
$var wire 1 o _057_ $end
$var wire 1 p _058_ $end
$var wire 1 q _059_ $end
$var wire 1 r _060_ $end
$var wire 1 s _061_ $end
$var wire 1 t _062_ $end
$var wire 1 u _063_ $end
$var wire 1 v _064_ $end
$var wire 1 w _065_ $end
$var wire 1 x _066_ $end
$var wire 1 ( clk $end
$var wire 4 y d [3:0] $end
$var wire 1 * dir $end
$var wire 1 + enb $end
$var wire 2 z mode [1:0] $end
$var wire 4 { q [3:0] $end
$var wire 1 . s_in $end
$var wire 1 / s_out $end
$scope module _067_ $end
$var wire 1 + A $end
$var wire 1 8 Y $end
$upscope $end
$scope module _068_ $end
$var wire 1 | A $end
$var wire 1 9 Y $end
$upscope $end
$scope module _069_ $end
$var wire 1 } A $end
$var wire 1 : Y $end
$upscope $end
$scope module _070_ $end
$var wire 1 : A $end
$var wire 1 9 B $end
$var wire 1 ; Y $end
$upscope $end
$scope module _071_ $end
$var wire 1 ; A $end
$var wire 1 8 B $end
$var wire 1 < Y $end
$upscope $end
$scope module _072_ $end
$var wire 1 < A $end
$var wire 1 = Y $end
$upscope $end
$scope module _073_ $end
$var wire 1 = A $end
$var wire 1 / B $end
$var wire 1 > Y $end
$upscope $end
$scope module _074_ $end
$var wire 1 * A $end
$var wire 1 ? Y $end
$upscope $end
$scope module _075_ $end
$var wire 1 ? A $end
$var wire 1 ~ B $end
$var wire 1 @ Y $end
$upscope $end
$scope module _076_ $end
$var wire 1 * A $end
$var wire 1 !" B $end
$var wire 1 A Y $end
$upscope $end
$scope module _077_ $end
$var wire 1 A A $end
$var wire 1 @ B $end
$var wire 1 B Y $end
$upscope $end
$scope module _078_ $end
$var wire 1 "" A $end
$var wire 1 #" B $end
$var wire 1 C Y $end
$upscope $end
$scope module _079_ $end
$var wire 1 C A $end
$var wire 1 D Y $end
$upscope $end
$scope module _080_ $end
$var wire 1 D A $end
$var wire 1 8 B $end
$var wire 1 E Y $end
$upscope $end
$scope module _081_ $end
$var wire 1 E A $end
$var wire 1 B B $end
$var wire 1 F Y $end
$upscope $end
$scope module _082_ $end
$var wire 1 F A $end
$var wire 1 > B $end
$var wire 1 7 Y $end
$upscope $end
$scope module _083_ $end
$var wire 1 8 A $end
$var wire 1 $" B $end
$var wire 1 G Y $end
$upscope $end
$scope module _084_ $end
$var wire 1 %" A $end
$var wire 1 9 B $end
$var wire 1 H Y $end
$upscope $end
$scope module _085_ $end
$var wire 1 &" A $end
$var wire 1 * B $end
$var wire 1 I Y $end
$upscope $end
$scope module _086_ $end
$var wire 1 I A $end
$var wire 1 @ B $end
$var wire 1 J Y $end
$upscope $end
$scope module _087_ $end
$var wire 1 J A $end
$var wire 1 H B $end
$var wire 1 K Y $end
$upscope $end
$scope module _088_ $end
$var wire 1 '" A $end
$var wire 1 L Y $end
$upscope $end
$scope module _089_ $end
$var wire 1 : A $end
$var wire 1 (" B $end
$var wire 1 M Y $end
$upscope $end
$scope module _090_ $end
$var wire 1 M A $end
$var wire 1 L B $end
$var wire 1 N Y $end
$upscope $end
$scope module _091_ $end
$var wire 1 )" A $end
$var wire 1 *" B $end
$var wire 1 O Y $end
$upscope $end
$scope module _092_ $end
$var wire 1 O A $end
$var wire 1 +" B $end
$var wire 1 P Y $end
$upscope $end
$scope module _093_ $end
$var wire 1 P A $end
$var wire 1 N B $end
$var wire 1 Q Y $end
$upscope $end
$scope module _094_ $end
$var wire 1 Q A $end
$var wire 1 K B $end
$var wire 1 R Y $end
$upscope $end
$scope module _095_ $end
$var wire 1 . A $end
$var wire 1 S Y $end
$upscope $end
$scope module _096_ $end
$var wire 1 S A $end
$var wire 1 * B $end
$var wire 1 T Y $end
$upscope $end
$scope module _097_ $end
$var wire 1 I A $end
$var wire 1 C B $end
$var wire 1 U Y $end
$upscope $end
$scope module _098_ $end
$var wire 1 U A $end
$var wire 1 T B $end
$var wire 1 V Y $end
$upscope $end
$scope module _099_ $end
$var wire 1 V A $end
$var wire 1 8 B $end
$var wire 1 W Y $end
$upscope $end
$scope module _100_ $end
$var wire 1 W A $end
$var wire 1 R B $end
$var wire 1 X Y $end
$upscope $end
$scope module _101_ $end
$var wire 1 X A $end
$var wire 1 G B $end
$var wire 1 ," Y $end
$upscope $end
$scope module _102_ $end
$var wire 1 < A $end
$var wire 1 -" B $end
$var wire 1 Y Y $end
$upscope $end
$scope module _103_ $end
$var wire 1 ." A $end
$var wire 1 9 B $end
$var wire 1 Z Y $end
$upscope $end
$scope module _104_ $end
$var wire 1 Z A $end
$var wire 1 /" B $end
$var wire 1 [ Y $end
$upscope $end
$scope module _105_ $end
$var wire 1 0" A $end
$var wire 1 * B $end
$var wire 1 \ Y $end
$upscope $end
$scope module _106_ $end
$var wire 1 ? A $end
$var wire 1 1" B $end
$var wire 1 ] Y $end
$upscope $end
$scope module _107_ $end
$var wire 1 ] A $end
$var wire 1 \ B $end
$var wire 1 ^ Y $end
$upscope $end
$scope module _108_ $end
$var wire 1 ^ A $end
$var wire 1 2" B $end
$var wire 1 _ Y $end
$upscope $end
$scope module _109_ $end
$var wire 1 _ A $end
$var wire 1 [ B $end
$var wire 1 ` Y $end
$upscope $end
$scope module _110_ $end
$var wire 1 ` A $end
$var wire 1 8 B $end
$var wire 1 a Y $end
$upscope $end
$scope module _111_ $end
$var wire 1 a A $end
$var wire 1 Y B $end
$var wire 1 3" Y $end
$upscope $end
$scope module _112_ $end
$var wire 1 < A $end
$var wire 1 4" B $end
$var wire 1 b Y $end
$upscope $end
$scope module _113_ $end
$var wire 1 Z A $end
$var wire 1 5" B $end
$var wire 1 c Y $end
$upscope $end
$scope module _114_ $end
$var wire 1 * A $end
$var wire 1 6" B $end
$var wire 1 d Y $end
$upscope $end
$scope module _115_ $end
$var wire 1 7" A $end
$var wire 1 ? B $end
$var wire 1 e Y $end
$upscope $end
$scope module _116_ $end
$var wire 1 e A $end
$var wire 1 d B $end
$var wire 1 f Y $end
$upscope $end
$scope module _117_ $end
$var wire 1 f A $end
$var wire 1 8" B $end
$var wire 1 g Y $end
$upscope $end
$scope module _118_ $end
$var wire 1 g A $end
$var wire 1 c B $end
$var wire 1 h Y $end
$upscope $end
$scope module _119_ $end
$var wire 1 h A $end
$var wire 1 8 B $end
$var wire 1 i Y $end
$upscope $end
$scope module _120_ $end
$var wire 1 i A $end
$var wire 1 b B $end
$var wire 1 9" Y $end
$upscope $end
$scope module _121_ $end
$var wire 1 8 A $end
$var wire 1 :" B $end
$var wire 1 j Y $end
$upscope $end
$scope module _122_ $end
$var wire 1 ;" A $end
$var wire 1 ? B $end
$var wire 1 k Y $end
$upscope $end
$scope module _123_ $end
$var wire 1 k A $end
$var wire 1 A B $end
$var wire 1 l Y $end
$upscope $end
$scope module _124_ $end
$var wire 1 l A $end
$var wire 1 H B $end
$var wire 1 m Y $end
$upscope $end
$scope module _125_ $end
$var wire 1 <" A $end
$var wire 1 n Y $end
$upscope $end
$scope module _126_ $end
$var wire 1 M A $end
$var wire 1 n B $end
$var wire 1 o Y $end
$upscope $end
$scope module _127_ $end
$var wire 1 =" A $end
$var wire 1 >" B $end
$var wire 1 p Y $end
$upscope $end
$scope module _128_ $end
$var wire 1 p A $end
$var wire 1 ?" B $end
$var wire 1 q Y $end
$upscope $end
$scope module _129_ $end
$var wire 1 q A $end
$var wire 1 o B $end
$var wire 1 r Y $end
$upscope $end
$scope module _130_ $end
$var wire 1 r A $end
$var wire 1 m B $end
$var wire 1 s Y $end
$upscope $end
$scope module _131_ $end
$var wire 1 S A $end
$var wire 1 ? B $end
$var wire 1 t Y $end
$upscope $end
$scope module _132_ $end
$var wire 1 k A $end
$var wire 1 C B $end
$var wire 1 u Y $end
$upscope $end
$scope module _133_ $end
$var wire 1 u A $end
$var wire 1 t B $end
$var wire 1 v Y $end
$upscope $end
$scope module _134_ $end
$var wire 1 v A $end
$var wire 1 8 B $end
$var wire 1 w Y $end
$upscope $end
$scope module _135_ $end
$var wire 1 w A $end
$var wire 1 s B $end
$var wire 1 x Y $end
$upscope $end
$scope module _136_ $end
$var wire 1 x A $end
$var wire 1 j B $end
$var wire 1 @" Y $end
$upscope $end
$scope module _137_ $end
$var wire 1 ( C $end
$var wire 1 A" D $end
$var reg 1 B" Q $end
$upscope $end
$scope module _138_ $end
$var wire 1 ( C $end
$var wire 1 C" D $end
$var reg 1 D" Q $end
$upscope $end
$scope module _139_ $end
$var wire 1 ( C $end
$var wire 1 E" D $end
$var reg 1 F" Q $end
$upscope $end
$scope module _140_ $end
$var wire 1 ( C $end
$var wire 1 G" D $end
$var reg 1 H" Q $end
$upscope $end
$scope module _141_ $end
$var wire 1 ( C $end
$var wire 1 7 D $end
$var reg 1 I" Q $end
$upscope $end
$upscope $end
$upscope $end
$enddefinitions $end
#0
$dumpvars
xI"
xH"
1G"
xF"
0E"
xD"
1C"
xB"
0A"
1@"
0?"
1>"
x="
1<"
x;"
x:"
09"
18"
x7"
x6"
05"
x4"
13"
12"
x1"
x0"
1/"
1."
x-"
0,"
0+"
1*"
x)"
0("
0'"
x&"
1%"
x$"
0#"
1""
x!"
x~
1}
0|
bx {
b10 z
b1010 y
0x
1w
0v
1u
0t
1s
0r
1q
xp
1o
0n
1m
xl
xk
1j
1i
0h
0g
xf
xe
1d
1c
0b
0a
1`
0_
x^
x]
1\
0[
0Z
0Y
1X
1W
0V
1U
1T
0S
0R
1Q
1P
xO
0N
1M
1L
1K
xJ
1I
0H
1G
1F
0E
1D
0C
xB
1A
x@
1?
1>
0=
1<
0;
0:
19
08
07
b1010 6
15
b10 4
13
02
b1010 1
00
x/
1.
bx -
b10 ,
1+
0*
b1010 )
0(
x'
z&
z%
z$
z#
z"
z!
$end
#5
0^
1f
0l
1B
1J
1O
1]
0e
1k
0@
0p
0!"
0$"
0)"
01"
1&"
1-"
17"
00"
04"
0;"
1~
16"
1:"
1="
0B"
1D"
0F"
1H"
b1010 -
b1010 {
0I"
0/
10
1(
#10
1A"
1,"
0G"
0@"
0X
1E"
1x
19"
1R
17
0C"
0w
0i
03"
b101 6
0Q
0F
1v
1h
1a
1N
1E
0U
0u
0c
0`
0M
0D
1C
1Z
1_
1p
1:
0}
0""
0%"
0*"
0."
02"
08"
0>"
b0 4
b0 ,
b0 z
00
0(
#15
1G"
0E"
1C"
1@"
09"
13"
b1011 6
0x
1i
0a
07
1w
0h
1`
1F
0v
1g
0_
0B
0J
1l
1u
0f
1^
1@
0k
1e
0]
0~
06"
0:"
0="
10"
14"
1;"
0&"
0-"
07"
1!"
1$"
1)"
11"
1I"
1/
0H"
1F"
0D"
1B"
b101 -
b101 {
10
1(
#20
00
0(
#25
1E"
0G"
19"
0@"
b111 6
0i
1x
1h
0w
17
0g
1v
0F
1f
0l
0u
1B
1J
0e
1k
0@
1&"
1-"
17"
00"
04"
0;"
1~
16"
1:"
1="
1D"
0F"
1H"
b1011 -
b1011 {
0I"
0/
10
1(
#30
00
0(
#35
1G"
1@"
b1111 6
0x
07
1w
1F
0v
0B
0J
1l
1u
1@
0k
0~
06"
0:"
0="
10"
14"
1;"
1I"
1/
0H"
1F"
b111 -
b111 {
10
1(
#40
00
0(
#45
17
0F
1B
1J
0@
1~
16"
1:"
1="
1H"
b1111 -
b1111 {
0I"
0/
10
1(
#50
0A"
0,"
1X
0E"
09"
b1010 6
0R
07
1i
1Q
1F
0h
0N
0E
1U
1c
1M
1D
0C
0O
0Z
0p
0:
1}
1""
1%"
1*"
1."
12"
18"
1>"
b10 4
b10 ,
b10 z
00
0(
#55
0l
0^
1k
1O
1]
00"
04"
0;"
0!"
0$"
0)"
01"
0F"
0B"
b1010 -
b1010 {
10
1(
#60
1A"
1,"
0X
1E"
19"
1R
0C"
0i
03"
b1101 6
0Q
1h
1a
1N
1E
0B
0u
0c
0`
0M
0D
1@
1e
1t
1C
1Z
1_
1p
0I
0T
0d
1:
0?
0}
0""
0%"
0*"
0."
02"
08"
0>"
12
1*
b0 4
b0 ,
b0 z
00
0(
#65
0A"
1C"
0,"
13"
b1110 6
1X
0a
17
0W
1`
0F
1V
0_
1B
1l
0J
0U
1^
0A
1I
0\
1!"
1$"
1)"
11"
0&"
0-"
07"
10"
14"
1;"
1B"
0D"
1F"
b1101 -
b1101 {
10
1(
#70
00
0(
#75
1A"
1,"
b1111 6
0X
1W
07
0V
1F
1J
1U
0B
0l
0I
1A
1&"
1-"
17"
0!"
0$"
0)"
01"
1I"
1/
1D"
0B"
b1110 -
b1110 {
10
1(
#80
00
0(
#85
17
0F
1B
1l
0A
1!"
1$"
1)"
11"
1B"
b1111 -
b1111 {
0I"
0/
10
1(
#90
00
0(
#95
1I"
1/
10
1(
#100
0G"
0@"
1x
0C"
0E"
03"
09"
b1 6
0s
07
1a
1i
1r
1F
0`
0h
0o
0E
1u
1[
1c
1M
1D
0C
0O
0Z
0p
0L
1n
0:
1'"
0/"
0<"
1}
1""
1%"
1*"
1."
12"
18"
1>"
b1 1
b1 )
b1 y
b10 4
b10 ,
b10 z
00
0(
#105
0J
0^
0f
1I
1\
1d
1p
0&"
0-"
07"
00"
04"
0;"
0~
06"
0:"
0="
0D"
0F"
0H"
b1 -
b1 {
0I"
0/
10
1(
#110
1C"
0A"
13"
0,"
b10 6
0a
1X
1`
0R
1Q
1^
1o
0P
0[
0c
0B
0l
1H
0]
0t
0M
1O
1Z
0_
1g
0q
1A
1T
09
1:
1?
1|
0}
0""
1#"
0%"
1("
0*"
1+"
0."
02"
08"
0>"
1?"
02
0*
b1 4
b1 ,
b1 z
00
0(
#115
1E"
0C"
19"
03"
b100 6
0i
1a
1h
0`
0g
1_
1f
0^
0e
1]
1&"
1-"
17"
0!"
0$"
0)"
01"
1D"
0B"
b10 -
b10 {
10
1(
#120
00
0(
#125
0E"
1G"
09"
1@"
b1000 6
1i
0x
0h
1s
1g
0m
0f
1l
1e
0k
0&"
0-"
07"
10"
14"
1;"
0D"
1F"
b100 -
b100 {
10
1(
#130
00
0(
#135
1A"
0G"
1,"
0@"
b1 6
0X
1x
1R
0s
0K
1m
1B
1J
0l
0@
1k
1~
16"
1:"
1="
00"
04"
0;"
1H"
0F"
b1000 -
b1000 {
10
1(
#140
00
0(
#145
1C"
0A"
13"
0,"
b10 6
0a
1X
1`
0R
0_
1K
1^
0B
0J
0]
1@
1!"
1$"
1)"
11"
0~
06"
0:"
0="
1B"
0H"
b1 -
b1 {
10
1(
#150
0C"
03"
1G"
1@"
b1000 6
1a
0x
0`
1s
1_
0m
0^
1B
1l
1]
1t
0A
0T
0?
12
1*
00
0(
#155
1E"
0G"
19"
0@"
b100 6
0i
1x
1h
0s
0g
1m
1f
0B
0l
0d
1A
1~
16"
1:"
1="
0!"
0$"
0)"
01"
1H"
0B"
b1000 -
b1000 {
10
1(
#160
00
0(
#165
1C"
0E"
13"
09"
b10 6
0a
1i
1`
0h
0_
1g
1^
0f
0\
1d
10"
14"
1;"
0~
06"
0:"
0="
1F"
0H"
b100 -
b100 {
10
1(
#170
00
0(
#175
0C"
1A"
03"
1,"
b1 6
1a
0X
0`
1R
1_
0K
0^
1J
1\
0I
00"
04"
0;"
1&"
1-"
17"
0F"
1D"
b10 -
b10 {
10
1(
#180
00
0(
#185
1G"
0A"
1@"
0,"
b1000 6
0x
1X
1s
0R
0m
1K
1B
1l
0J
0A
1I
1!"
1$"
1)"
11"
0&"
0-"
07"
1B"
0D"
b1 -
b1 {
10
1(
