Tarea5/register4B-cond.v
module reg_desp(s_out,clk,enb,dir,s_in,mode,d,q);
input clk,enb,dir,s_in;
input [1:0] mode;
input [3:0] d;
output reg [3:0] q;
output reg s_out;
always @(posedge clk)
  begin
    if(enb==1'b1)
      begin
        if(mode==2'b00)
          begin
            if(dir==1'b0)
              begin
                q<={q[2:0],s_in};
                s_out<=q[3];
              end
            else if(dir==1'b1)
              begin
                q<={s_in,q[3:1]};
                s_out<=q[0];
              end
          end
        else if(mode ==2'b01)
          begin
            if(dir==1'b0)
              begin
                s_out<=0;
                q<={q[2:0],q[3]};
              end
            else if(dir==1'b1)
              begin
                s_out<=0;
                q<={q[0],q[3:1]};
              end
          end
        else if(mode == 2'b10)
          begin
            s_out<=0;
            q<=d;
          end
      end
  end
endmodule

Tarea5/tester.v
//IE-0523 Circuitos Digitales II
//Tarea 2. Tester de Regitro Desplazable de 4 bits
//Estudiante:	Cesar Valverde Zuñiga		A86605		
//II Ciclo 2017

//Modulo Tester 4 bits
module tester(clk,enb,dir,s_in,modo,d);
	//Salidas.
	output reg clk,enb,dir,s_in;
	output reg [1:0] modo;
	output reg [3:0] d;

//Señal de Reloj / Frecuencia del reloj
always #2 clk = !clk;

initial begin
	//Valores Iniciales
	enb <= 0;
	clk <=0;
	dir <= 0;
	s_in <= 1;
	modo <= 2'b00;
    
	$display("Inicia Prueba #5, Carga en Paralelo");
	modo <= 2'b10;
	enb <= 1'b1;
	d <= 4'b0001;
	#4; //Retardo
   
	$display("Inicia Prueba #4, Rotacion Circular a la Derecha");
	modo <= 2'b01;
	dir <= 1'b1;
	#16

	$display("Inicia Prueba #3, Rotacion Circular a la Izquierda");
	modo <= 2'b01;
	dir <= 1'b0;
	#16;
  
	$display("Inicia Prueba #2, Rotacion a la Derecha");
	modo <= 2'b00;
	dir <= 1'b1;
	#16;
	
	//$display("Inicia Prueba #1, Rotacion a la Izquierda");
	modo <= 2'b10;
	enb <= 1'b1;
	d <= 4'b0001;
	#4;
     
	$display("Inicia Prueba #1, Rotacion a la Izquierda");
	modo <= 2'b00;
	dir <= 1'b0;
	#16;
	$finish;
    end
endmodule

Tarea5/registrodesp_tb.v
//IE-0523 Circuitos Digitales II
//Tarea 2. Test Bench del Registro Desplazable de 4 bits
//Estudiante:	Cesar Valverde Zuñiga		A86605		
//II Ciclo 2017

//Definicion del modulo
module testbench();

wire [1:0] modo;
wire [3:0] d;
output wire [3:0] q;

//Intanciando Modulos
tester test1(clk,enb,dir,s_in,modo,d);
reg_desp reg1(s_out,clk,enb,dir,s_in,modo,d,q);

//Resultados en Terminal
initial
  begin
    $dumpfile("registro.vcd");
    $dumpvars;
    $display ("time\t clk enb dir s_in modo d q s_out");
    $monitor ("%g\t    %b  %b  %b  %b %b %b %b  %b",
    $time, clk, enb, dir, s_in, modo, d, q, s_out);
  end
endmodule

Tarea5/registro.vcd
$date
	Fri Sep  8 15:26:07 2017
$end
$version
	Icarus Verilog
$end
$timescale
	1s
$end
$scope module testbench $end
$var wire 1 ! s_out $end
$var wire 1 " s_in $end
$var wire 4 # q [3:0] $end
$var wire 2 $ modo [1:0] $end
$var wire 1 % enb $end
$var wire 1 & dir $end
$var wire 4 ' d [3:0] $end
$var wire 1 ( clk $end
$scope module reg1 $end
$var wire 1 " s_in $end
$var wire 2 ) mode [1:0] $end
$var wire 1 % enb $end
$var wire 1 & dir $end
$var wire 4 * d [3:0] $end
$var wire 1 ( clk $end
$var reg 4 + q [3:0] $end
$var reg 1 ! s_out $end
$upscope $end
$scope module test1 $end
$var reg 1 ( clk $end
$var reg 4 , d [3:0] $end
$var reg 1 & dir $end
$var reg 1 % enb $end
$var reg 2 - modo [1:0] $end
$var reg 1 " s_in $end
$upscope $end
$upscope $end
$enddefinitions $end
#0
$dumpvars
b10 -
b1 ,
bx +
b1 *
b10 )
0(
b1 '
0&
1%
b10 $
bx #
1"
x!
$end
#2
b1 #
b1 +
0!
1(
#4
1&
b1 $
b1 )
b1 -
0(
#6
b1000 #
b1000 +
1(
#8
0(
#10
b100 #
b100 +
1(
#12
0(
#14
b10 #
b10 +
1(
#16
0(
#18
b1 #
b1 +
1(
#20
0&
0(
#22
b10 #
b10 +
1(
#24
0(
#26
b100 #
b100 +
1(
#28
0(
#30
b1000 #
b1000 +
1(
#32
0(
#34
b1 #
b1 +
1(
#36
1&
b0 $
b0 )
b0 -
0(
#38
1!
b1000 #
b1000 +
1(
#40
0(
#42
0!
b1100 #
b1100 +
1(
#44
0(
#46
b1110 #
b1110 +
1(
#48
0(
#50
b1111 #
b1111 +
1(
#52
b10 $
b10 )
b10 -
0(
#54
b1 #
b1 +
1(
#56
0&
b0 $
b0 )
b0 -
0(
#58
b11 #
b11 +
1(
#60
0(
#62
b111 #
b111 +
1(
#64
0(
#66
b1111 #
b1111 +
1(
#68
0(
#70
1!
1(
